[{"holes":[{"centerline":[{"lat":42.0830076,"lng":-76.848802},{"lat":42.0843493,"lng":-76.8487161},{"lat":42.0857069,"lng":-76.8496549}],"defaultPin":{"lat":42.0857069,"lng":-76.8496549},"handicap":1,"id":"osm:w136629918:1","number":1,"par":4,"surfaces":[],"tees":[{"coordinates":{"lat":42.0830076,"lng":-76.848802},"handicap":1,"par":4,"teeColor":"tee1","yardage":349}],"yardages":[{"teeColor":"tee1","yardage":349}]},{"centerline":[{"lat":42.0863319,"lng":-76.8487242},{"lat":42.0878885,"lng":-76.8486196},{"lat":42.0887404,"lng":-76.8485713}],"defaultPin":{"lat":42.0887404,"lng":-76.8485713},"handicap":2,"id":"osm:w136629918:2","number":2,"par":4,"surfaces":[],"tees":[{"coordinates":{"lat":42.0863319,"lng":-76.8487242},"handicap":2,"par":4,"teeColor":"tee1","yardage":293}],"yardages":[{"teeColor":"tee1","yardage":293}]},{"centerline":[{"lat":42.0901318,"lng":-76.8480536},{"lat":42.0911608,"lng":-76.8479866},{"lat":42.0915032,"lng":-76.8477345},{"lat":42.0920724,"lng":-76.8469244}],"defaultPin":{"lat":42.0920724,"lng":-76.8469244},"handicap":3,"id":"osm:w136629918:3","number":3,"par":4,"surfaces":[],"tees":[{"coordinates":{"lat":42.0901318,"lng":-76.8480536},"handicap":3,"par":4,"teeColor":"tee1","yardage":273}],"yardages":[{"teeColor":"tee1","yardage":273}]},{"centerline":[{"lat":42.092363,"lng":-76.8468011},{"lat":42.0919829,"lng":-76.8481931}],"defaultPin":{"lat":42.0919829,"lng":-76.8481931},"handicap":4,"id":"osm:w136629918:4","number":4,"par":3,"surfaces":[],"tees":[{"coordinates":{"lat":42.092363,"lng":-76.8468011},"handicap":4,"par":3,"teeColor":"tee1","yardage":134}],"yardages":[{"teeColor":"tee1","yardage":134}]},{"centerline":[{"lat":42.0924347,"lng":-76.8475896},{"lat":42.0935493,"lng":-76.8459803},{"lat":42.0943096,"lng":-76.8455994},{"lat":42.0951614,"lng":-76.8449503},{"lat":42.0955714,"lng":-76.8436521}],"defaultPin":{"lat":42.0955714,"lng":-76.8436521},"handicap":5,"id":"osm:w136629918:5","number":5,"par":5,"surfaces":[],"tees":[{"coordinates":{"lat":42.0924347,"lng":-76.8475896},"handicap":5,"par":5,"teeColor":"tee1","yardage":544}],"yardages":[{"teeColor":"tee1","yardage":544}]},{"centerline":[{"lat":42.0957386,"lng":-76.8431479},{"lat":42.0939155,"lng":-76.8440974},{"lat":42.0925382,"lng":-76.8440893}],"defaultPin":{"lat":42.0925382,"lng":-76.8440893},"handicap":6,"id":"osm:w136629918:6","number":6,"par":4,"surfaces":[],"tees":[{"coordinates":{"lat":42.0957386,"lng":-76.8431479},"handicap":6,"par":4,"teeColor":"tee1","yardage":405}],"yardages":[{"teeColor":"tee1","yardage":405}]},{"centerline":[{"lat":42.0929681,"lng":-76.8445104},{"lat":42.0917161,"lng":-76.8453003}],"defaultPin":{"lat":42.0917161,"lng":-76.8453003},"handicap":7,"id":"osm:w136629918:7","number":7,"par":3,"surfaces":[{"notes":"OSM · edited 2022","polygon":[{"lat":42.0922416,"lng":-76.845134},{"lat":42.0922356,"lng":-76.8452561},{"lat":42.0921769,"lng":-76.8453191},{"lat":42.0921282,"lng":-76.8453164},{"lat":42.0920665,"lng":-76.8452842},{"lat":42.0919361,"lng":-76.845362},{"lat":42.0918575,"lng":-76.8453446},{"lat":42.0918216,"lng":-76.8452521},{"lat":42.0918266,"lng":-76.8451796},{"lat":42.0918734,"lng":-76.8450657},{"lat":42.091948,"lng":-76.8449865},{"lat":42.0921242,"lng":-76.8448792},{"lat":42.0921879,"lng":-76.8449624},{"lat":42.0922317,"lng":-76.8450562}],"type":"water"}],"tees":[{"coordinates":{"lat":42.0929681,"lng":-76.8445104},"handicap":7,"par":3,"teeColor":"tee1","yardage":168}],"yardages":[{"teeColor":"tee1","yardage":168}]},{"centerline":[{"lat":42.09132,"lng":-76.8451139},{"lat":42.0899666,"lng":-76.846152},{"lat":42.0890291,"lng":-76.8479061}],"defaultPin":{"lat":42.0890291,"lng":-76.8479061},"handicap":8,"id":"osm:w136629918:8","number":8,"par":4,"surfaces":[],"tees":[{"coordinates":{"lat":42.09132,"lng":-76.8451139},"handicap":8,"par":4,"teeColor":"tee1","yardage":384}],"yardages":[{"teeColor":"tee1","yardage":384}]},{"centerline":[{"lat":42.0887932,"lng":-76.8479598},{"lat":42.0864553,"lng":-76.8481368},{"lat":42.0851754,"lng":-76.8485633}],"defaultPin":{"lat":42.0851754,"lng":-76.8485633},"handicap":9,"id":"osm:w136629918:9","number":9,"par":4,"surfaces":[],"tees":[{"coordinates":{"lat":42.0887932,"lng":-76.8479598},"handicap":9,"par":4,"teeColor":"tee1","yardage":445}],"yardages":[{"teeColor":"tee1","yardage":445}]},{"centerline":[{"lat":42.0853366,"lng":-76.8476835},{"lat":42.086937,"lng":-76.8473697},{"lat":42.0885235,"lng":-76.8474501}],"defaultPin":{"lat":42.0885235,"lng":-76.8474501},"handicap":10,"id":"osm:w136629918:10","number":10,"par":5,"surfaces":[],"tees":[{"coordinates":{"lat":42.0853366,"lng":-76.8476835},"handicap":10,"par":5,"teeColor":"tee1","yardage":390}],"yardages":[{"teeColor":"tee1","yardage":390}]},{"centerline":[{"lat":42.0888738,"lng":-76.8472704},{"lat":42.085661,"lng":-76.844371}],"defaultPin":{"lat":42.085661,"lng":-76.844371},"handicap":11,"id":"osm:w136629918:11","number":11,"par":4,"surfaces":[{"notes":"OSM · edited 2022","polygon":[{"lat":42.0859895,"lng":-76.8448886},{"lat":42.0859527,"lng":-76.8449382},{"lat":42.0859039,"lng":-76.8449289},{"lat":42.085884,"lng":-76.8448189},{"lat":42.0859139,"lng":-76.8446633},{"lat":42.0859537,"lng":-76.8446083},{"lat":42.0860104,"lng":-76.8446164},{"lat":42.0860244,"lng":-76.8446459},{"lat":42.0860045,"lng":-76.8447438},{"lat":42.0860074,"lng":-76.8448269}],"type":"water"}],"tees":[{"coordinates":{"lat":42.0888738,"lng":-76.8472704},"handicap":11,"par":4,"teeColor":"tee1","yardage":470}],"yardages":[{"teeColor":"tee1","yardage":470}]},{"centerline":[{"lat":42.0859995,"lng":-76.8442073},{"lat":42.0878606,"lng":-76.8425417},{"lat":42.0882085,"lng":-76.8420207}],"defaultPin":{"lat":42.0882085,"lng":-76.8420207},"handicap":12,"id":"osm:w136629918:12","number":12,"par":4,"surfaces":[],"tees":[{"coordinates":{"lat":42.0859995,"lng":-76.8442073},"handicap":12,"par":4,"teeColor":"tee1","yardage":335}],"yardages":[{"teeColor":"tee1","yardage":335}]},{"centerline":[{"lat":42.0881074,"lng":-76.841391},{"lat":42.0856439,"lng":-76.8440381}],"defaultPin":{"lat":42.0856439,"lng":-76.8440381},"handicap":13,"id":"osm:w136629918:13","number":13,"par":4,"surfaces":[],"tees":[{"coordinates":{"lat":42.0881074,"lng":-76.841391},"handicap":13,"par":4,"teeColor":"tee1","yardage":383}],"yardages":[{"teeColor":"tee1","yardage":383}]},{"centerline":[{"lat":42.0854441,"lng":-76.8432002},{"lat":42.0867409,"lng":-76.8417666},{"lat":42.0875332,"lng":-76.841273}],"defaultPin":{"lat":42.0875332,"lng":-76.841273},"handicap":14,"id":"osm:w136629918:14","number":14,"par":4,"surfaces":[],"tees":[{"coordinates":{"lat":42.0854441,"lng":-76.8432002},"handicap":14,"par":4,"teeColor":"tee1","yardage":310}],"yardages":[{"teeColor":"tee1","yardage":310}]},{"centerline":[{"lat":42.0868674,"lng":-76.841273},{"lat":42.0854799,"lng":-76.8410879}],"defaultPin":{"lat":42.0854799,"lng":-76.8410879},"handicap":15,"id":"osm:w136629918:15","number":15,"par":3,"surfaces":[],"tees":[{"coordinates":{"lat":42.0868674,"lng":-76.841273},"handicap":15,"par":3,"teeColor":"tee1","yardage":170}],"yardages":[{"teeColor":"tee1","yardage":170}]},{"centerline":[{"lat":42.0851973,"lng":-76.8416593},{"lat":42.0849226,"lng":-76.8441457},{"lat":42.0850301,"lng":-76.8445319},{"lat":42.085257,"lng":-76.8449342},{"lat":42.086527,"lng":-76.8464363}],"defaultPin":{"lat":42.086527,"lng":-76.8464363},"handicap":16,"id":"osm:w136629918:16","number":16,"par":5,"surfaces":[{"notes":"OSM · edited 2022","polygon":[{"lat":42.0857327,"lng":-76.8423888},{"lat":42.0852192,"lng":-76.842539},{"lat":42.0851097,"lng":-76.8424881},{"lat":42.085044,"lng":-76.8423432},{"lat":42.085052,"lng":-76.8420669},{"lat":42.0851057,"lng":-76.8418899},{"lat":42.0851794,"lng":-76.8418121},{"lat":42.0852888,"lng":-76.8418041},{"lat":42.0854819,"lng":-76.8420589},{"lat":42.0856651,"lng":-76.8421286},{"lat":42.0857566,"lng":-76.8422064},{"lat":42.0857785,"lng":-76.8422681},{"lat":42.0857626,"lng":-76.8423191}],"type":"water"}],"tees":[{"coordinates":{"lat":42.0851973,"lng":-76.8416593},"handicap":16,"par":5,"teeColor":"tee1","yardage":515}],"yardages":[{"teeColor":"tee1","yardage":515}]},{"centerline":[{"lat":42.0866584,"lng":-76.846911},{"lat":42.0847792,"lng":-76.8456101},{"lat":42.0842617,"lng":-76.8442637}],"defaultPin":{"lat":42.0842617,"lng":-76.8442637},"handicap":17,"id":"osm:w136629918:17","number":17,"par":4,"surfaces":[],"tees":[{"coordinates":{"lat":42.0866584,"lng":-76.846911},"handicap":17,"par":4,"teeColor":"tee1","yardage":394}],"yardages":[{"teeColor":"tee1","yardage":394}]},{"centerline":[{"lat":42.0840666,"lng":-76.8441349},{"lat":42.084186,"lng":-76.8469191},{"lat":42.0837163,"lng":-76.8480188}],"defaultPin":{"lat":42.0837163,"lng":-76.8480188},"handicap":18,"id":"osm:w136629918:18","number":18,"par":4,"surfaces":[],"tees":[{"coordinates":{"lat":42.0840666,"lng":-76.8441349},"handicap":18,"par":4,"teeColor":"tee1","yardage":366}],"yardages":[{"teeColor":"tee1","yardage":366}]}],"id":"osm:w136629918","location":{"coordinates":{"lat":42.088302575507065,"lng":-76.84585178570931}},"name":"Elmira Country Club","ratings":[],"vendor":"osm","vendorId":"w136629918"}]