[{"holes":[{"centerline":[{"lat":42.2447955,"lng":-79.4615514},{"lat":42.2417376,"lng":-79.4592983}],"defaultPin":{"lat":42.2417376,"lng":-79.4592983},"handicap":1,"id":"osm:w136094766:1","number":1,"par":4,"surfaces":[],"tees":[{"coordinates":{"lat":42.2447955,"lng":-79.4615514},"handicap":1,"par":4,"teeColor":"tee1","yardage":424}],"yardages":[{"teeColor":"tee1","yardage":424}]},{"centerline":[{"lat":42.2414258,"lng":-79.4590444},{"lat":42.2411161,"lng":-79.4603962}],"defaultPin":{"lat":42.2411161,"lng":-79.4603962},"handicap":2,"id":"osm:w136094766:2","number":2,"par":3,"surfaces":[],"tees":[{"coordinates":{"lat":42.2414258,"lng":-79.4590444},"handicap":2,"par":3,"teeColor":"tee1","yardage":127}],"yardages":[{"teeColor":"tee1","yardage":127}]},{"centerline":[{"lat":42.2412829,"lng":-79.4607932},{"lat":42.2428317,"lng":-79.4607181},{"lat":42.2444281,"lng":-79.4622308}],"defaultPin":{"lat":42.2444281,"lng":-79.4622308},"handicap":3,"id":"osm:w136094766:3","number":3,"par":4,"surfaces":[],"tees":[{"coordinates":{"lat":42.2412829,"lng":-79.4607932},"handicap":3,"par":4,"teeColor":"tee1","yardage":426}],"yardages":[{"teeColor":"tee1","yardage":426}]},{"centerline":[{"lat":42.2446287,"lng":-79.4627208},{"lat":42.243527,"lng":-79.4619773},{"lat":42.2422181,"lng":-79.4615245}],"defaultPin":{"lat":42.2422181,"lng":-79.4615245},"handicap":4,"id":"osm:w136094766:4","number":4,"par":4,"surfaces":[],"tees":[{"coordinates":{"lat":42.2446287,"lng":-79.4627208},"handicap":4,"par":4,"teeColor":"tee1","yardage":314}],"yardages":[{"teeColor":"tee1","yardage":314}]},{"centerline":[{"lat":42.2423531,"lng":-79.4620663},{"lat":42.240153,"lng":-79.4607681}],"defaultPin":{"lat":42.240153,"lng":-79.4607681},"handicap":5,"id":"osm:w136094766:5","number":5,"par":4,"surfaces":[],"tees":[{"coordinates":{"lat":42.2423531,"lng":-79.4620663},"handicap":5,"par":4,"teeColor":"tee1","yardage":292}],"yardages":[{"teeColor":"tee1","yardage":292}]},{"centerline":[{"lat":42.2402523,"lng":-79.4613797},{"lat":42.2426113,"lng":-79.4626993}],"defaultPin":{"lat":42.2426113,"lng":-79.4626993},"handicap":6,"id":"osm:w136094766:6","number":6,"par":4,"surfaces":[],"tees":[{"coordinates":{"lat":42.2402523,"lng":-79.4613797},"handicap":6,"par":4,"teeColor":"tee1","yardage":310}],"yardages":[{"teeColor":"tee1","yardage":310}]},{"centerline":[{"lat":42.2423412,"lng":-79.4618518},{"lat":42.2442474,"lng":-79.4632841}],"defaultPin":{"lat":42.2442474,"lng":-79.4632841},"handicap":7,"id":"osm:w136094766:7","number":7,"par":4,"surfaces":[],"tees":[{"coordinates":{"lat":42.2423412,"lng":-79.4618518},"handicap":7,"par":4,"teeColor":"tee1","yardage":265}],"yardages":[{"teeColor":"tee1","yardage":265}]},{"centerline":[{"lat":42.2446846,"lng":-79.4634832},{"lat":42.2449706,"lng":-79.46454}],"defaultPin":{"lat":42.2449706,"lng":-79.46454},"handicap":8,"id":"osm:w136094766:8","number":8,"par":3,"surfaces":[],"tees":[{"coordinates":{"lat":42.2446846,"lng":-79.4634832},"handicap":8,"par":3,"teeColor":"tee1","yardage":101}],"yardages":[{"teeColor":"tee1","yardage":101}]},{"centerline":[{"lat":42.245052,"lng":-79.4638462},{"lat":42.2448097,"lng":-79.4625132}],"defaultPin":{"lat":42.2448097,"lng":-79.4625132},"handicap":9,"id":"osm:w136094766:9","number":9,"par":3,"surfaces":[{"notes":"OSM · edited 2025","polygon":[{"lat":42.2457287,"lng":-79.462761},{"lat":42.2457545,"lng":-79.462761},{"lat":42.2458227,"lng":-79.4626915},{"lat":42.2458219,"lng":-79.4626759},{"lat":42.2456746,"lng":-79.4624878},{"lat":42.245625,"lng":-79.4625286}],"type":"water"}],"tees":[{"coordinates":{"lat":42.245052,"lng":-79.4638462},"handicap":9,"par":3,"teeColor":"tee1","yardage":124}],"yardages":[{"teeColor":"tee1","yardage":124}]}],"id":"osm:w136094766","location":{"coordinates":{"lat":42.24272518664462,"lng":-79.46152593920583}},"name":"Chautauqua Point","ratings":[],"vendor":"osm","vendorId":"w136094766"}]