[{"holes":[{"centerline":[{"lat":32.825382,"lng":-86.6077781},{"lat":32.8231611,"lng":-86.608088},{"lat":32.8221508,"lng":-86.6079667},{"lat":32.821319,"lng":-86.6079209}],"defaultPin":{"lat":32.821319,"lng":-86.6079209},"handicap":1,"id":"osm:w242270785:1","number":1,"par":5,"surfaces":[],"tees":[{"coordinates":{"lat":32.825382,"lng":-86.6077781},"handicap":1,"par":5,"teeColor":"tee1","yardage":497}],"yardages":[{"teeColor":"tee1","yardage":497}]},{"centerline":[{"lat":32.82112,"lng":-86.6080376},{"lat":32.8209634,"lng":-86.6094071}],"defaultPin":{"lat":32.8209634,"lng":-86.6094071},"handicap":2,"id":"osm:w242270785:2","number":2,"par":3,"surfaces":[],"tees":[{"coordinates":{"lat":32.82112,"lng":-86.6080376},"handicap":2,"par":3,"teeColor":"tee1","yardage":141}],"yardages":[{"teeColor":"tee1","yardage":141}]},{"centerline":[{"lat":32.8205106,"lng":-86.6093879},{"lat":32.8208278,"lng":-86.6077352},{"lat":32.8210998,"lng":-86.6071199}],"defaultPin":{"lat":32.8210998,"lng":-86.6071199},"handicap":3,"id":"osm:w242270785:3","number":3,"par":4,"surfaces":[],"tees":[{"coordinates":{"lat":32.8205106,"lng":-86.6093879},"handicap":3,"par":4,"teeColor":"tee1","yardage":244}],"yardages":[{"teeColor":"tee1","yardage":244}]},{"centerline":[{"lat":32.8219464,"lng":-86.606163},{"lat":32.8239563,"lng":-86.6062467},{"lat":32.8251926,"lng":-86.6060367}],"defaultPin":{"lat":32.8251926,"lng":-86.6060367},"handicap":4,"id":"osm:w242270785:4","number":4,"par":4,"surfaces":[],"tees":[{"coordinates":{"lat":32.8219464,"lng":-86.606163},"handicap":4,"par":4,"teeColor":"tee1","yardage":396}],"yardages":[{"teeColor":"tee1","yardage":396}]},{"centerline":[{"lat":32.8258841,"lng":-86.6061695},{"lat":32.8265685,"lng":-86.6075356}],"defaultPin":{"lat":32.8265685,"lng":-86.6075356},"handicap":5,"id":"osm:w242270785:5","number":5,"par":3,"surfaces":[],"tees":[{"coordinates":{"lat":32.8258841,"lng":-86.6061695},"handicap":5,"par":3,"teeColor":"tee1","yardage":163}],"yardages":[{"teeColor":"tee1","yardage":163}]},{"centerline":[{"lat":32.8264521,"lng":-86.6077568},{"lat":32.8265627,"lng":-86.6090553}],"defaultPin":{"lat":32.8265627,"lng":-86.6090553},"handicap":6,"id":"osm:w242270785:6","number":6,"par":3,"surfaces":[],"tees":[{"coordinates":{"lat":32.8264521,"lng":-86.6077568},"handicap":6,"par":3,"teeColor":"tee1","yardage":133}],"yardages":[{"teeColor":"tee1","yardage":133}]},{"centerline":[{"lat":32.8262865,"lng":-86.6092191},{"lat":32.8258511,"lng":-86.6073223},{"lat":32.8255145,"lng":-86.606126}],"defaultPin":{"lat":32.8255145,"lng":-86.606126},"handicap":7,"id":"osm:w242270785:7","number":7,"par":4,"surfaces":[],"tees":[{"coordinates":{"lat":32.8262865,"lng":-86.6092191},"handicap":7,"par":4,"teeColor":"tee1","yardage":330}],"yardages":[{"teeColor":"tee1","yardage":330}]},{"centerline":[{"lat":32.8252297,"lng":-86.6067119},{"lat":32.8233647,"lng":-86.6067744},{"lat":32.8217701,"lng":-86.6069479}],"defaultPin":{"lat":32.8217701,"lng":-86.6069479},"handicap":8,"id":"osm:w242270785:8","number":8,"par":4,"surfaces":[],"tees":[{"coordinates":{"lat":32.8252297,"lng":-86.6067119},"handicap":8,"par":4,"teeColor":"tee1","yardage":422}],"yardages":[{"teeColor":"tee1","yardage":422}]},{"centerline":[{"lat":32.82146,"lng":-86.6073015},{"lat":32.8232238,"lng":-86.6073933},{"lat":32.8249638,"lng":-86.6072654}],"defaultPin":{"lat":32.8249638,"lng":-86.6072654},"handicap":9,"id":"osm:w242270785:9","number":9,"par":4,"surfaces":[],"tees":[{"coordinates":{"lat":32.82146,"lng":-86.6073015},"handicap":9,"par":4,"teeColor":"tee1","yardage":427}],"yardages":[{"teeColor":"tee1","yardage":427}]}],"id":"osm:w242270785","location":{"address":"1 Country Club Road","city":"Clanton","coordinates":{"lat":32.824999031461154,"lng":-86.6078345097314}},"name":"Clanton Country Club","ratings":[],"vendor":"osm","vendorId":"w242270785"}]