[{"holes":[{"centerline":[{"lat":40.3608794,"lng":-79.9860173},{"lat":40.3609716,"lng":-79.990435}],"defaultPin":{"lat":40.3609716,"lng":-79.990435},"handicap":1,"id":"osm:w317784559:1","number":1,"par":4,"surfaces":[],"tees":[{"coordinates":{"lat":40.3608794,"lng":-79.9860173},"handicap":1,"par":4,"teeColor":"tee1","yardage":409}],"yardages":[{"teeColor":"tee1","yardage":409}]},{"centerline":[{"lat":40.3612409,"lng":-79.9900723},{"lat":40.3619447,"lng":-79.9878679},{"lat":40.3626972,"lng":-79.9839462}],"defaultPin":{"lat":40.3626972,"lng":-79.9839462},"handicap":2,"id":"osm:w317784559:2","number":2,"par":5,"surfaces":[],"tees":[{"coordinates":{"lat":40.3612409,"lng":-79.9900723},"handicap":2,"par":5,"teeColor":"tee1","yardage":596}],"yardages":[{"teeColor":"tee1","yardage":596}]},{"centerline":[{"lat":40.3624659,"lng":-79.9835657},{"lat":40.3610785,"lng":-79.984236},{"lat":40.3599618,"lng":-79.9843977}],"defaultPin":{"lat":40.3599618,"lng":-79.9843977},"handicap":3,"id":"osm:w317784559:3","number":3,"par":4,"surfaces":[],"tees":[{"coordinates":{"lat":40.3624659,"lng":-79.9835657},"handicap":3,"par":4,"teeColor":"tee1","yardage":316}],"yardages":[{"teeColor":"tee1","yardage":316}]},{"centerline":[{"lat":40.3596943,"lng":-79.9849718},{"lat":40.359778,"lng":-79.9827681}],"defaultPin":{"lat":40.359778,"lng":-79.9827681},"handicap":4,"id":"osm:w317784559:4","number":4,"par":3,"surfaces":[],"tees":[{"coordinates":{"lat":40.3596943,"lng":-79.9849718},"handicap":4,"par":3,"teeColor":"tee1","yardage":204}],"yardages":[{"teeColor":"tee1","yardage":204}]},{"centerline":[{"lat":40.3591914,"lng":-79.9821864},{"lat":40.3592573,"lng":-79.9845161},{"lat":40.3588316,"lng":-79.9862294}],"defaultPin":{"lat":40.3588316,"lng":-79.9862294},"handicap":5,"id":"osm:w317784559:5","number":5,"par":4,"surfaces":[],"tees":[{"coordinates":{"lat":40.3591914,"lng":-79.9821864},"handicap":5,"par":4,"teeColor":"tee1","yardage":383}],"yardages":[{"teeColor":"tee1","yardage":383}]},{"centerline":[{"lat":40.3591333,"lng":-79.9868466},{"lat":40.3564999,"lng":-79.9852246}],"defaultPin":{"lat":40.3564999,"lng":-79.9852246},"handicap":6,"id":"osm:w317784559:6","number":6,"par":4,"surfaces":[],"tees":[{"coordinates":{"lat":40.3591333,"lng":-79.9868466},"handicap":6,"par":4,"teeColor":"tee1","yardage":354}],"yardages":[{"teeColor":"tee1","yardage":354}]},{"centerline":[{"lat":40.3564077,"lng":-79.9855172},{"lat":40.3547561,"lng":-79.9851717}],"defaultPin":{"lat":40.3547561,"lng":-79.9851717},"handicap":7,"id":"osm:w317784559:7","number":7,"par":3,"surfaces":[],"tees":[{"coordinates":{"lat":40.3564077,"lng":-79.9855172},"handicap":7,"par":3,"teeColor":"tee1","yardage":203}],"yardages":[{"teeColor":"tee1","yardage":203}]},{"centerline":[{"lat":40.3557484,"lng":-79.9848181},{"lat":40.3540733,"lng":-79.9836194},{"lat":40.3537665,"lng":-79.9821621}],"defaultPin":{"lat":40.3537665,"lng":-79.9821621},"handicap":8,"id":"osm:w317784559:8","number":8,"par":4,"surfaces":[],"tees":[{"coordinates":{"lat":40.3557484,"lng":-79.9848181},"handicap":8,"par":4,"teeColor":"tee1","yardage":372}],"yardages":[{"teeColor":"tee1","yardage":372}]},{"centerline":[{"lat":40.3529206,"lng":-79.9816552},{"lat":40.3543791,"lng":-79.9868405}],"defaultPin":{"lat":40.3543791,"lng":-79.9868405},"handicap":9,"id":"osm:w317784559:9","number":9,"par":5,"surfaces":[{"notes":"OSM · edited 2024","polygon":[{"lat":40.3542479,"lng":-79.9866203},{"lat":40.3542556,"lng":-79.9867273},{"lat":40.3542448,"lng":-79.9867613},{"lat":40.3541976,"lng":-79.9868},{"lat":40.3541724,"lng":-79.986789},{"lat":40.3541499,"lng":-79.9867534},{"lat":40.3541361,"lng":-79.9866916},{"lat":40.3541445,"lng":-79.9866295},{"lat":40.3541695,"lng":-79.9865931},{"lat":40.3542028,"lng":-79.9865846},{"lat":40.3542303,"lng":-79.9866008}],"type":"water"}],"tees":[{"coordinates":{"lat":40.3529206,"lng":-79.9816552},"handicap":9,"par":5,"teeColor":"tee1","yardage":512}],"yardages":[{"teeColor":"tee1","yardage":512}]},{"centerline":[{"lat":40.3543718,"lng":-79.9847842},{"lat":40.3551541,"lng":-79.9876248},{"lat":40.3561108,"lng":-79.9903158}],"defaultPin":{"lat":40.3561108,"lng":-79.9903158},"handicap":10,"id":"osm:w317784559:10","number":10,"par":5,"surfaces":[{"notes":"OSM · edited 2024","polygon":[{"lat":40.3545221,"lng":-79.9863155},{"lat":40.3545008,"lng":-79.9862618},{"lat":40.3545148,"lng":-79.9861555},{"lat":40.3545641,"lng":-79.9860597},{"lat":40.3546053,"lng":-79.9860616},{"lat":40.3546623,"lng":-79.9860988},{"lat":40.3546989,"lng":-79.9861447},{"lat":40.3547134,"lng":-79.9862091},{"lat":40.3547086,"lng":-79.9862718},{"lat":40.3546682,"lng":-79.986339},{"lat":40.3545938,"lng":-79.9863709},{"lat":40.3545322,"lng":-79.9863434}],"type":"water"},{"notes":"OSM · edited 2024","polygon":[{"lat":40.3548685,"lng":-79.986138},{"lat":40.3548445,"lng":-79.9860958},{"lat":40.3547862,"lng":-79.9859021},{"lat":40.3547967,"lng":-79.9858455},{"lat":40.3548401,"lng":-79.9858487},{"lat":40.3549034,"lng":-79.9858951},{"lat":40.3549902,"lng":-79.9859043},{"lat":40.355056,"lng":-79.9859692},{"lat":40.355092,"lng":-79.9860819},{"lat":40.3550931,"lng":-79.9861551},{"lat":40.3550722,"lng":-79.9862063},{"lat":40.3550153,"lng":-79.9862507},{"lat":40.3549571,"lng":-79.9862697},{"lat":40.354932,"lng":-79.9862589},{"lat":40.3548947,"lng":-79.986202}],"type":"water"}],"tees":[{"coordinates":{"lat":40.3543718,"lng":-79.9847842},"handicap":10,"par":5,"teeColor":"tee1","yardage":555}],"yardages":[{"teeColor":"tee1","yardage":555}]},{"centerline":[{"lat":40.3563263,"lng":-79.9900054},{"lat":40.3557881,"lng":-79.9878824},{"lat":40.3551677,"lng":-79.9859219}],"defaultPin":{"lat":40.3551677,"lng":-79.9859219},"handicap":11,"id":"osm:w317784559:11","number":11,"par":4,"surfaces":[],"tees":[{"coordinates":{"lat":40.3563263,"lng":-79.9900054},"handicap":11,"par":4,"teeColor":"tee1","yardage":404}],"yardages":[{"teeColor":"tee1","yardage":404}]},{"centerline":[{"lat":40.3554732,"lng":-79.9859176},{"lat":40.3565658,"lng":-79.9859139}],"defaultPin":{"lat":40.3565658,"lng":-79.9859139},"handicap":12,"id":"osm:w317784559:12","number":12,"par":3,"surfaces":[],"tees":[{"coordinates":{"lat":40.3554732,"lng":-79.9859176},"handicap":12,"par":3,"teeColor":"tee1","yardage":133}],"yardages":[{"teeColor":"tee1","yardage":133}]},{"centerline":[{"lat":40.3573675,"lng":-79.986483},{"lat":40.3576473,"lng":-79.988774},{"lat":40.3576875,"lng":-79.9897464}],"defaultPin":{"lat":40.3576875,"lng":-79.9897464},"handicap":13,"id":"osm:w317784559:13","number":13,"par":4,"surfaces":[],"tees":[{"coordinates":{"lat":40.3573675,"lng":-79.986483},"handicap":13,"par":4,"teeColor":"tee1","yardage":305}],"yardages":[{"teeColor":"tee1","yardage":305}]},{"centerline":[{"lat":40.3583798,"lng":-79.9903728},{"lat":40.3578513,"lng":-79.9876815},{"lat":40.3577738,"lng":-79.9867496}],"defaultPin":{"lat":40.3577738,"lng":-79.9867496},"handicap":14,"id":"osm:w317784559:14","number":14,"par":4,"surfaces":[],"tees":[{"coordinates":{"lat":40.3583798,"lng":-79.9903728},"handicap":14,"par":4,"teeColor":"tee1","yardage":344}],"yardages":[{"teeColor":"tee1","yardage":344}]},{"centerline":[{"lat":40.3583496,"lng":-79.9872033},{"lat":40.3588804,"lng":-79.9891181}],"defaultPin":{"lat":40.3588804,"lng":-79.9891181},"handicap":15,"id":"osm:w317784559:15","number":15,"par":3,"surfaces":[],"tees":[{"coordinates":{"lat":40.3583496,"lng":-79.9872033},"handicap":15,"par":3,"teeColor":"tee1","yardage":189}],"yardages":[{"teeColor":"tee1","yardage":189}]},{"centerline":[{"lat":40.3591157,"lng":-79.9887388},{"lat":40.3595091,"lng":-79.9869503},{"lat":40.3596689,"lng":-79.9852942}],"defaultPin":{"lat":40.3596689,"lng":-79.9852942},"handicap":16,"id":"osm:w317784559:16","number":16,"par":4,"surfaces":[],"tees":[{"coordinates":{"lat":40.3591157,"lng":-79.9887388},"handicap":16,"par":4,"teeColor":"tee1","yardage":327}],"yardages":[{"teeColor":"tee1","yardage":327}]},{"centerline":[{"lat":40.3599967,"lng":-79.9864069},{"lat":40.3595331,"lng":-79.9884248},{"lat":40.3594254,"lng":-79.9902919}],"defaultPin":{"lat":40.3594254,"lng":-79.9902919},"handicap":17,"id":"osm:w317784559:17","number":17,"par":4,"surfaces":[],"tees":[{"coordinates":{"lat":40.3599967,"lng":-79.9864069},"handicap":17,"par":4,"teeColor":"tee1","yardage":369}],"yardages":[{"teeColor":"tee1","yardage":369}]},{"centerline":[{"lat":40.3601185,"lng":-79.9905656},{"lat":40.3604403,"lng":-79.9860548}],"defaultPin":{"lat":40.3604403,"lng":-79.9860548},"handicap":18,"id":"osm:w317784559:18","number":18,"par":4,"surfaces":[],"tees":[{"coordinates":{"lat":40.3601185,"lng":-79.9905656},"handicap":18,"par":4,"teeColor":"tee1","yardage":420}],"yardages":[{"teeColor":"tee1","yardage":420}]}],"id":"osm:w317784559","location":{"address":"4305 Brownsville Road","city":"Pittsburgh","coordinates":{"lat":40.35825957658093,"lng":-79.98618886924643}},"name":"South Hills Country Club","ratings":[],"vendor":"osm","vendorId":"w317784559"}]